{
  "file_name": "互联网上网服务营业场所检查信息202506302138.xlsx",
  "table_name": "互联网上网服务营业场所检查信息202506302138",
  "row_count": 65,
  "columns": [
    "ccrwmc",
    "xh",
    "ccjcjg",
    "jcssjg",
    "qyjgmc",
    "tyshxydm"
  ],
  "fields": [
    {
      "name": "ccrwmc",
      "type": "VARCHAR",
      "length": 255,
      "nullable": false,
      "primary_key": false,
      "semantic": "company_name",
      "enum_values": [
        "对互联网上网服务营业场所的检查",
        "2024年对互联网上网服务营业场所的检查"
      ],
      "value_pool": [
        "对互联网上网服务营业场所的检查",
        "2024年对互联网上网服务营业场所的检查"
      ],
      "min_value": null,
      "max_value": null
    },
    {
      "name": "xh",
      "type": "INT",
      "length": null,
      "nullable": false,
      "primary_key": true,
      "semantic": "id",
      "enum_values": [],
      "value_pool": [
        "2",
        "3",
        "4",
        "5",
        "6",
        "7",
        "8",
        "9",
        "10",
        "11",
        "12",
        "13",
        "14",
        "15",
        "16",
        "17",
        "18",
        "19",
        "20",
        "21",
        "22",
        "23",
        "24",
        "25",
        "26",
        "27",
        "28",
        "29",
        "30",
        "31",
        "32",
        "33",
        "34",
        "35",
        "36",
        "37",
        "38",
        "40",
        "41",
        "42",
        "43",
        "44",
        "45",
        "46",
        "47",
        "48",
        "49",
        "50",
        "51",
        "52",
        "53",
        "54",
        "55",
        "56",
        "57",
        "58",
        "59",
        "60",
        "61",
        "62",
        "63",
        "64",
        "65",
        "66",
        "67"
      ],
      "min_value": 2.0,
      "max_value": 67.0
    },
    {
      "name": "ccjcjg",
      "type": "VARCHAR",
      "length": 255,
      "nullable": false,
      "primary_key": false,
      "semantic": "unknown",
      "enum_values": [
        "无违规"
      ],
      "value_pool": [
        "无违规"
      ],
      "min_value": null,
      "max_value": null
    },
    {
      "name": "jcssjg",
      "type": "VARCHAR",
      "length": 255,
      "nullable": false,
      "primary_key": false,
      "semantic": "unknown",
      "enum_values": [
        "梁山县文化和旅游局"
      ],
      "value_pool": [
        "梁山县文化和旅游局"
      ],
      "min_value": null,
      "max_value": null
    },
    {
      "name": "qyjgmc",
      "type": "VARCHAR",
      "length": 255,
      "nullable": false,
      "primary_key": false,
      "semantic": "company_name",
      "enum_values": [],
      "value_pool": [
        "梁山县蓝吧网络中心",
        "梁山中鲁时空雷狐网吧加盟店",
        "梁山万佳网络飞速连锁店",
        "梁山县泰和网吧",
        "梁山县星雨网吧",
        "梁山中鲁时空飞腾网吧加盟店",
        "梁山县顺心网吧",
        "梁山万佳网络腾飞加盟店",
        "梁山县万佳网络闪速加盟店",
        "梁山万佳网络龙行天下网吧加盟店",
        "梁山县万佳网络七彩雨加盟店",
        "梁山太阳雨网吧",
        "梁山爱书人蓝月亮连锁网吧",
        "梁山县爱网人朋友网吧加盟店",
        "梁山县万佳网络王中王网吧加盟店",
        "梁山县万佳网络小霸王网吧加盟店",
        "梁山县万佳网络雨宁溪网吧",
        "梁山县万佳网络新浪潮加盟店",
        "梁山县星光网吧",
        "梁山县圆梦网吧",
        "梁山县长宏网吧",
        "梁山县现代网吧",
        "梁山爱书人天涯网吧加盟店",
        "梁山万佳网络网事如风加盟店",
        "梁山县先锋网吧",
        "梁山万佳网络梦幻星空加盟店",
        "梁山爱书人飞宇网吧加盟店",
        "梁山县蓝色梦幻网吧",
        "梁山中鲁时空蓝精灵网吧加盟店",
        "梁山县爱书人胜通网吧加盟店",
        "梁山县万佳网络聊聊加盟店",
        "梁山万佳网络速腾加盟店",
        "梁山中鲁时空金海岸网吧加盟店",
        "梁山爱书人广圣网吧加盟店",
        "梁山县万佳网络天方夜谭加盟店",
        "梁山县天翔网吧",
        "梁山县相约网吧",
        "梁山爱书人浪漫家园网吧加盟店",
        "梁山县龙海网吧",
        "梁山麦田网咖",
        "梁山未来电子竞技馆",
        "梁山揽月网络服务有限公司"
      ],
      "min_value": null,
      "max_value": null
    },
    {
      "name": "tyshxydm",
      "type": "VARCHAR",
      "length": 255,
      "nullable": false,
      "primary_key": false,
      "semantic": "unknown",
      "enum_values": [],
      "value_pool": [
        "91370832MA3D15MC13",
        "91370832MA3C64F29C",
        "91370832MA3C5J4G9R",
        "91370832MA3D15NW19",
        "91370832MA3D15N183",
        "91370832MA3D0WUL45",
        "91370832MA3D15NR03",
        "91370832MA3D0WUM20",
        "91370832MA3D15MDXT",
        "91370832MA3D0X2A9K",
        "91370832MA3D15NT7R",
        "91370832MA3D15KG1U",
        "91370832MA3D0WR11W",
        "91370832MA3D15LK0H",
        "91370832MA3D15NP4D",
        "91370832MA3D15MF6M",
        "91370832MA3D15N69B",
        "91370832796195981B",
        "91370832MA3D15NBXE",
        "91370832MA3D15NA1N",
        "91370832MA3D15M46A",
        "91370832MA3D15LL9E",
        "91370832MA3D0WLM5H",
        "91370832MA3D0WUK6A",
        "91370832MA3D15N50E",
        "91370832MA3D0X194D",
        "91370832MA3D0WTA8H",
        "91370832MA3D15N851",
        "91370832MA3D0WLN3C",
        "91370832MA3C8HEE7A",
        "91370832MA3D0WTD22",
        "91370832MA3D0X2B7E",
        "91370832MA3D0WMU7K",
        "91370832MA3D0WWT2T",
        "91370832MA3D15NQ28",
        "91370832MA3D15ME8T",
        "91370832MA3D15M545",
        "91370832MA3D0X178P",
        "91370832MA3D15N93U",
        "91370832MAE3GK3L8E",
        "91370832MAE35XXN0E",
        "91370832MAE1LD02XA"
      ],
      "min_value": null,
      "max_value": null
    }
  ]
}