{
  "file_name": "农村低收入群体危房改造信息202508010310.xlsx",
  "table_name": "农村低收入群体危房改造信息202508010310",
  "row_count": 264,
  "columns": [
    "cmwyh",
    "zj",
    "xsq",
    "hzxm",
    "pkhlx"
  ],
  "fields": [
    {
      "name": "cmwyh",
      "type": "VARCHAR",
      "length": 255,
      "nullable": false,
      "primary_key": false,
      "semantic": "unknown",
      "enum_values": [],
      "value_pool": [
        "村民委员会",
        "北白石村",
        "北丑村",
        "贺庄村",
        "刘家洼",
        "刘家洼村",
        "南丑村",
        "上下峪",
        "寺台",
        "寺台村",
        "西头",
        "大黄沟村",
        "东华村",
        "凤凰庄村",
        "两泉沟村",
        "南崇义",
        "邢家屋村",
        "大沟崖",
        "东高",
        "凤凰岭",
        "尖山",
        "沙胡同",
        "石佛",
        "于庄",
        "官园",
        "黑砚滩村",
        "三角湾",
        "东岩店村",
        "后王庄村",
        "黄阴集村",
        "孔家铺",
        "龙虎庄",
        "龙云岗",
        "苗馆村",
        "三山口",
        "尚岩",
        "西故安",
        "肖家庄",
        "肖家庄村",
        "小李家庄村",
        "安久村",
        "安乐",
        "北泽沟",
        "卞桥二村",
        "附马井",
        "韩家村",
        "灰泉村",
        "李家寨",
        "历东村",
        "两泉村",
        "临湖村",
        "柳河村",
        "马连村",
        "马泉庄",
        "南石匣",
        "南泽沟",
        "聂家村",
        "三合村",
        "石缝泉",
        "西泽沟",
        "荀家岭",
        "余粮村",
        "御驾道"
      ],
      "min_value": null,
      "max_value": null
    },
    {
      "name": "zj",
      "type": "VARCHAR",
      "length": 255,
      "nullable": false,
      "primary_key": false,
      "semantic": "unknown",
      "enum_values": [
        "镇街",
        "高峪镇",
        "华村镇",
        "济河街道",
        "金庄镇",
        "苗馆镇",
        "泉林镇"
      ],
      "value_pool": [
        "镇街",
        "高峪镇",
        "华村镇",
        "济河街道",
        "金庄镇",
        "苗馆镇",
        "泉林镇"
      ],
      "min_value": null,
      "max_value": null
    },
    {
      "name": "xsq",
      "type": "VARCHAR",
      "length": 255,
      "nullable": false,
      "primary_key": false,
      "semantic": "unknown",
      "enum_values": [
        "县市区",
        "泗水县"
      ],
      "value_pool": [
        "县市区",
        "泗水县"
      ],
      "min_value": null,
      "max_value": null
    },
    {
      "name": "hzxm",
      "type": "VARCHAR",
      "length": 255,
      "nullable": false,
      "primary_key": false,
      "semantic": "person_name",
      "enum_values": [],
      "value_pool": [
        "户***",
        "王**",
        "周**",
        "蒋**",
        "宋**",
        "姜**",
        "李**",
        "刘**",
        "马**",
        "陈**",
        "董**",
        "段**",
        "杨**",
        "张**",
        "郝**",
        "吕**",
        "范**",
        "孙**",
        "于**",
        "秦**",
        "孔**",
        "代**",
        "常**",
        "贺**",
        "赵**",
        "魏**",
        "尹**",
        "尤**",
        "徐**",
        "韩**",
        "郎**",
        "荀**",
        "南**",
        "唐**",
        "康**",
        "薛**",
        "冯**",
        "芦**",
        "聂**",
        "巩**",
        "高**"
      ],
      "min_value": null,
      "max_value": null
    },
    {
      "name": "pkhlx",
      "type": "VARCHAR",
      "length": 255,
      "nullable": false,
      "primary_key": false,
      "semantic": "status",
      "enum_values": [
        "贫困户类型",
        "分散供养特困户",
        "低保户",
        "低保户/残疾"
      ],
      "value_pool": [
        "贫困户类型",
        "分散供养特困户",
        "低保户",
        "低保户/残疾"
      ],
      "min_value": null,
      "max_value": null
    }
  ]
}