{
  "file_name": "国家药品集中带量采购中选产品价格表_0.csv",
  "table_name": "国家药品集中带量采购中选产品价格表_0",
  "row_count": 113,
  "columns": [
    "pzmlbh",
    "mljx",
    "sbqymc",
    "zxbzdw",
    "jx",
    "pzxh",
    "zxqk",
    "zhb",
    "scqymc",
    "kpqymc",
    "zxzjdw",
    "sdzxjgy",
    "tym",
    "gg",
    "mltym",
    "bzcz",
    "mlgg",
    "ypdm",
    "cpi",
    "pzmc"
  ],
  "fields": [
    {
      "name": "pzmlbh",
      "type": "INT",
      "length": null,
      "nullable": false,
      "primary_key": true,
      "semantic": "id",
      "enum_values": [],
      "value_pool": [
        "isn00100",
        "isn00200",
        "isn00300",
        "isn00402",
        "isn00500",
        "isn00601",
        "isn00701",
        "isn00702",
        "isn00800",
        "isn00902",
        "isn01000",
        "isn01100",
        "isn01200",
        "isn01302",
        "isn01402",
        "isn01500",
        "isn01600",
        "isn01700",
        "isn01801",
        "isn01802",
        "isn01803",
        "isn01900",
        "isn02001",
        "isn02002",
        "isn02102",
        "isn02201",
        "isn02202",
        "isn02203",
        "isn02400",
        "isn02500",
        "isn02600",
        "isn02702",
        "isn02800",
        "isn02902",
        "isn03001",
        "isn03002",
        "isn03100",
        "isn03200",
        "isn03300",
        "isn03400",
        "isn03500",
        "isn03600",
        "isn03700",
        "isn03800",
        "isn03900",
        "isn04000",
        "isn04100",
        "isn04202",
        "isn04301",
        "isn04401",
        "isn04402",
        "isn04404",
        "isn04500",
        "isn04600",
        "isn04700",
        "isn04800",
        "isn04900"
      ],
      "min_value": null,
      "max_value": null
    },
    {
      "name": "mljx",
      "type": "VARCHAR",
      "length": 255,
      "nullable": true,
      "primary_key": false,
      "semantic": "unknown",
      "enum_values": [
        "口服常释剂型",
        "注射剂",
        "口腔崩解片",
        "缓释控释剂型",
        "颗粒剂",
        "0",
        "咀嚼片",
        "口服液体剂",
        "注射用浓溶液"
      ],
      "value_pool": [
        "口服常释剂型",
        "注射剂",
        "口腔崩解片",
        "缓释控释剂型",
        "颗粒剂",
        "0",
        "咀嚼片",
        "口服液体剂",
        "注射用浓溶液"
      ],
      "min_value": null,
      "max_value": null
    },
    {
      "name": "sbqymc",
      "type": "VARCHAR",
      "length": 255,
      "nullable": false,
      "primary_key": false,
      "semantic": "company_name",
      "enum_values": [],
      "value_pool": [
        "杭州中美华东制药有限公司",
        "正大天晴药业集团股份有限公司",
        "四川汇宇制药股份有限公司",
        "江苏正大清江制药有限公司",
        "山东裕欣药业有限公司",
        "广东东阳光药业有限公司",
        "山东罗欣药业集团股份有限公司",
        "华北制药股份有限公司",
        "黑龙江诺捷制药有限责任公司",
        "海南普利制药股份有限公司",
        "华东医药（西安）博华制药有限公司",
        "石药集团欧意药业有限公司",
        "江苏万邦生化医药集团有限责任公司",
        "扬子江药业集团江苏扬子江医药经营有限公司",
        "天方药业有限公司",
        "山西仟源医药集团股份有限公司",
        "齐鲁制药有限公司",
        "江西青峰药业有限公司",
        "石家庄以岭药业股份有限公司",
        "湖南洞庭药业股份有限公司",
        "浙江海正药业股份有限公司",
        "江苏恩华药业股份有限公司",
        "合肥英太制药有限公司",
        "江苏正大丰海制药有限公司",
        "南京长澳制药有限公司",
        "河北仁合益康药业有限公司",
        "江苏吴中医药集团有限公司苏州制药厂",
        "青岛百洋制药有限公司",
        "浙江华海药业股份有限公司",
        "杭州康恩贝制药有限公司",
        "福州海王福药制药有限公司",
        "上海汇伦江苏药业有限公司",
        "南京先声东元制药有限公司",
        "南京优科制药有限公司",
        "宜昌人福药业有限责任公司",
        "四川科伦药业股份有限公司",
        "鲁南新时代医药有限公司",
        "天大药业(珠海)有限公司",
        "山东华铂凯盛生物科技有限公司",
        "成都苑东生物制药股份有限公司",
        "广东华南药业集团有限公司",
        "四川康弘医药贸易有限公司",
        "重庆圣华曦药业股份有限公司",
        "湖南科伦制药有限公司"
      ],
      "min_value": null,
      "max_value": null
    },
    {
      "name": "zxbzdw",
      "type": "VARCHAR",
      "length": 255,
      "nullable": false,
      "primary_key": false,
      "semantic": "company_name",
      "enum_values": [
        "盒",
        "支",
        "瓶"
      ],
      "value_pool": [
        "盒",
        "支",
        "瓶"
      ],
      "min_value": null,
      "max_value": null
    },
    {
      "name": "jx",
      "type": "VARCHAR",
      "length": 255,
      "nullable": false,
      "primary_key": false,
      "semantic": "unknown",
      "enum_values": [],
      "value_pool": [
        "薄膜衣片",
        "注射用无菌粉末",
        "素片",
        "口腔崩解片",
        "肠溶胶囊",
        "缓释胶囊",
        "颗粒剂",
        "缓释片",
        "胶囊剂",
        "咀嚼片",
        "口服溶液剂",
        "注射液"
      ],
      "min_value": null,
      "max_value": null
    },
    {
      "name": "pzxh",
      "type": "INT",
      "length": null,
      "nullable": false,
      "primary_key": true,
      "semantic": "id",
      "enum_values": [],
      "value_pool": [
        "1.0",
        "2.0",
        "3.0",
        "4.2",
        "5.0",
        "6.1",
        "7.1",
        "7.2",
        "8.0",
        "9.2",
        "10.0",
        "11.0",
        "12.0",
        "13.2",
        "14.2",
        "15.0",
        "16.0",
        "17.0",
        "18.1",
        "18.2",
        "18.3",
        "19.0",
        "20.1",
        "20.2",
        "21.2",
        "22.1",
        "22.2",
        "22.3",
        "24.0",
        "25.0",
        "26.0",
        "27.2",
        "28.0",
        "29.2",
        "30.1",
        "30.2",
        "31.0",
        "32.0",
        "33.0",
        "34.0",
        "35.0",
        "36.0",
        "37.0",
        "38.0",
        "39.0",
        "40.0",
        "41.0",
        "42.2",
        "43.1",
        "44.1",
        "44.2",
        "44.4",
        "45.0",
        "46.0",
        "47.0",
        "48.0",
        "49.0"
      ],
      "min_value": 1.0,
      "max_value": 56.2
    },
    {
      "name": "zxqk",
      "type": "VARCHAR",
      "length": 255,
      "nullable": false,
      "primary_key": false,
      "semantic": "unknown",
      "enum_values": [
        "中选",
        "中选多包装",
        "供应",
        "中选供应",
        "供应多包装"
      ],
      "value_pool": [
        "中选",
        "中选多包装",
        "供应",
        "中选供应",
        "供应多包装"
      ],
      "min_value": null,
      "max_value": null
    },
    {
      "name": "zhb",
      "type": "INT",
      "length": null,
      "nullable": false,
      "primary_key": false,
      "semantic": "unknown",
      "enum_values": [],
      "value_pool": [
        "14",
        "28",
        "1",
        "12",
        "18",
        "90",
        "20",
        "24",
        "30",
        "7",
        "8",
        "60",
        "16",
        "10",
        "3",
        "48",
        "100",
        "5",
        "15",
        "45",
        "2"
      ],
      "min_value": 1.0,
      "max_value": 100.0
    },
    {
      "name": "scqymc",
      "type": "VARCHAR",
      "length": 255,
      "nullable": false,
      "primary_key": false,
      "semantic": "company_name",
      "enum_values": [],
      "value_pool": [
        "杭州中美华东制药有限公司",
        "正大天晴药业集团股份有限公司",
        "四川汇宇制药股份有限公司",
        "江苏正大清江制药有限公司",
        "山东裕欣药业有限公司",
        "广东东阳光药业有限公司",
        "山东罗欣药业集团股份有限公司",
        "华北制药股份有限公司",
        "黑龙江诺捷制药有限责任公司",
        "海南普利制药股份有限公司",
        "华东医药（西安）博华制药有限公司",
        "石药集团欧意药业有限公司",
        "江苏万邦生化医药集团有限责任公司",
        "扬子江药业集团四川海蓉药业有限公司",
        "天方药业有限公司",
        "山西仟源医药集团股份有限公司",
        "齐鲁制药有限公司",
        "江西青峰药业有限公司",
        "石家庄以岭药业股份有限公司",
        "湖南洞庭药业股份有限公司",
        "浙江海正药业股份有限公司",
        "江苏恩华药业股份有限公司",
        "合肥英太制药有限公司",
        "江苏正大丰海制药有限公司",
        "南京长澳制药有限公司",
        "河北仁合益康药业有限公司",
        "江苏吴中医药集团有限公司苏州制药厂",
        "青岛百洋制药有限公司",
        "浙江华海药业股份有限公司",
        "杭州康恩贝制药有限公司",
        "福州海王福药制药有限公司",
        "上海汇伦江苏药业有限公司",
        "南京先声东元制药有限公司",
        "南京优科制药有限公司",
        "宜昌人福药业有限责任公司",
        "四川科伦药业股份有限公司",
        "鲁南贝特制药有限公司",
        "天大药业(珠海)有限公司",
        "烟台鲁银药业有限公司",
        "成都苑东生物制药股份有限公司",
        "广东华南药业集团有限公司",
        "成都康弘药业集团股份有限公司",
        "重庆圣华曦药业股份有限公司",
        "湖南科伦制药有限公司"
      ],
      "min_value": null,
      "max_value": null
    },
    {
      "name": "kpqymc",
      "type": "VARCHAR",
      "length": 255,
      "nullable": false,
      "primary_key": false,
      "semantic": "company_name",
      "enum_values": [],
      "value_pool": [
        "杭州中美华东制药有限公司",
        "正大天晴药业集团股份有限公司",
        "四川汇宇制药股份有限公司",
        "江苏正大清江制药有限公司",
        "山东裕欣药业有限公司",
        "宜昌东阳光医药有限公司",
        "山东罗欣药业集团股份有限公司",
        "华北制药股份有限公司",
        "黑龙江诺捷制药有限责任公司",
        "浙江普利药业有限公司",
        "华东医药（西安）博华制药有限公司",
        "石药集团欧意药业有限公司",
        "江苏万邦医药营销有限公司",
        "扬子江药业集团江苏扬子江医药经营有限公司",
        "天方药业有限公司",
        "西藏仟源药业有限公司",
        "山西仟源医药集团股份有限公司",
        "山东万润医药有限公司",
        "江西青峰医药贸易有限公司",
        "齐鲁制药有限公司",
        "石家庄以岭药业股份有限公司",
        "湖南洞庭药业股份有限公司",
        "浙江海正药业股份有限公司",
        "江苏恩华和信医药营销有限公司",
        "合肥英太制药有限公司",
        "江苏正大丰海制药有限公司",
        "南京长澳制药有限公司",
        "河北仁合益康药业有限公司",
        "江苏吴中医药集团有限公司苏州制药厂",
        "青岛百洋制药有限公司",
        "浙江华海医药销售有限公司",
        "浙江康恩贝医药销售有限公司",
        "福州海王福药制药有限公司",
        "上海汇伦江苏药业有限公司",
        "江苏先声药业有限公司",
        "南京优科制药有限公司",
        "宜昌人福药业有限责任公司",
        "山东科伦医药贸易有限公司",
        "四川科伦药业股份有限公司",
        "鲁南新时代医药有限公司",
        "山东新时代药业有限公司",
        "天大药业(珠海)有限公司",
        "广东泰恩康医药股份有限公司",
        "西藏润禾药业有限公司",
        "广东众生医药贸易有限公司",
        "成都康弘药业集团股份有限公司",
        "四川康弘医药贸易有限公司",
        "重庆圣华曦药业股份有限公司"
      ],
      "min_value": null,
      "max_value": null
    },
    {
      "name": "zxzjdw",
      "type": "VARCHAR",
      "length": 255,
      "nullable": false,
      "primary_key": false,
      "semantic": "company_name",
      "enum_values": [
        "片",
        "瓶",
        "粒",
        "包",
        "袋",
        "支"
      ],
      "value_pool": [
        "片",
        "瓶",
        "粒",
        "包",
        "袋",
        "支"
      ],
      "min_value": null,
      "max_value": null
    },
    {
      "name": "sdzxjgy",
      "type": "DECIMAL",
      "length": null,
      "nullable": false,
      "primary_key": false,
      "semantic": "unknown",
      "enum_values": [],
      "value_pool": [
        "20.27",
        "50.83",
        "99.12",
        "260.0",
        "12.83",
        "18.96",
        "89.39",
        "1.5",
        "1.79",
        "2.22",
        "13.21",
        "1.69",
        "3.3",
        "1.48",
        "2.48",
        "2.88",
        "5.61",
        "8.04",
        "1.04",
        "11.33",
        "4.77",
        "2.63",
        "5.13",
        "1.18",
        "1.74",
        "3.4",
        "7.43",
        "16.48",
        "28.26",
        "69.0",
        "3.64",
        "7.1",
        "10.5",
        "20.41",
        "39.8",
        "24.98",
        "25.26",
        "18.99",
        "4.34",
        "8.47",
        "9.21",
        "27.6",
        "2.3",
        "11.0",
        "33.96",
        "31.51",
        "29.8",
        "85.88",
        "1.58",
        "9.88",
        "5.03",
        "9.81",
        "7.98",
        "11.17",
        "15.96",
        "22.34",
        "2.66",
        "21.4",
        "18.66",
        "36.38",
        "1.21",
        "2.35",
        "3.47",
        "4.68",
        "19.96",
        "38.92",
        "7.25",
        "15.1",
        "11.97",
        "9.45",
        "55.0",
        "11.78",
        "8.17",
        "18.45",
        "35.97",
        "70.14",
        "5.34",
        "1.22",
        "2.38",
        "4.64",
        "67.38",
        "7.48",
        "14.59",
        "12.72",
        "24.8",
        "21.62",
        "11.57",
        "4.3",
        "38.0",
        "28.0",
        "1.75"
      ],
      "min_value": 1.04,
      "max_value": 281.0
    },
    {
      "name": "tym",
      "type": "VARCHAR",
      "length": 255,
      "nullable": false,
      "primary_key": false,
      "semantic": "unknown",
      "enum_values": [],
      "value_pool": [
        "阿那曲唑片",
        "阿哌沙班片",
        "注射用阿扎胞苷",
        "盐酸氨基葡萄糖片",
        "盐酸氨溴索片",
        "奥氮平口崩片",
        "奥美拉唑肠溶胶囊",
        "布洛芬缓释胶囊",
        "布洛芬颗粒",
        "地氯雷他定片",
        "多潘立酮片",
        "盐酸二甲双胍缓释片",
        "盐酸二甲双胍片",
        "非布司他片",
        "非那雄胺片",
        "盐酸氟西汀胶囊",
        "枸橼酸西地那非片",
        "甲钴胺片",
        "卡培他滨片",
        "卡托普利片",
        "富马酸喹硫平片",
        "来曲唑片",
        "氯氮平片",
        "盐酸美金刚片",
        "孟鲁司特钠咀嚼片",
        "孟鲁司特钠颗粒",
        "匹伐他汀钙片",
        "琥珀酸普芦卡必利片",
        "盐酸曲美他嗪片",
        "塞来昔布胶囊",
        "盐酸舍曲林片",
        "盐酸坦索罗辛缓释胶囊",
        "碳酸氢钠片",
        "替格瑞洛片",
        "枸橼酸托法替布片",
        "维格列汀片",
        "维生素B6片",
        "氢溴酸西酞普兰片",
        "氢溴酸西酞普兰胶囊",
        "盐酸西替利嗪片",
        "缬沙坦胶囊",
        "盐酸达泊西汀片",
        "依托考昔片",
        "盐酸乙胺丁醇片",
        "右佐匹克隆片",
        "左乙拉西坦口服溶液",
        "左乙拉西坦注射用浓溶液",
        "阿莫西林颗粒"
      ],
      "min_value": null,
      "max_value": null
    },
    {
      "name": "gg",
      "type": "VARCHAR",
      "length": 255,
      "nullable": false,
      "primary_key": false,
      "semantic": "unknown",
      "enum_values": [],
      "value_pool": [
        "1mg",
        "2.5mg",
        "100mg",
        "0.75g",
        "30mg",
        "5mg",
        "10mg",
        "20mg",
        "0.3g",
        "0.2g",
        "0.5g",
        "40mg",
        "25mg",
        "50mg",
        "0.1g",
        "0.5mg",
        "0.15g",
        "0.5g:4mg",
        "2mg",
        "1mg(以普芦卡必利计）",
        "0.2mg",
        "90mg",
        "80mg",
        "60mg",
        "120mg",
        "0.25g",
        "3mg",
        "150ml(10%)",
        "5ml:500mg",
        "0.125g"
      ],
      "min_value": null,
      "max_value": null
    },
    {
      "name": "mltym",
      "type": "VARCHAR",
      "length": 255,
      "nullable": false,
      "primary_key": false,
      "semantic": "unknown",
      "enum_values": [],
      "value_pool": [
        "阿那曲唑",
        "阿哌沙班",
        "阿扎胞苷",
        "氨基葡萄糖",
        "氨溴索",
        "奥氮平",
        "奥美拉唑",
        "布洛芬",
        "地氯雷他定",
        "多潘立酮",
        "二甲双胍",
        "非布司他",
        "非那雄胺",
        "氟西汀",
        "枸橼酸西地那非片",
        "甲钴胺",
        "卡培他滨",
        "卡托普利",
        "喹硫平",
        "来曲唑",
        "氯氮平",
        "美金刚",
        "孟鲁司特",
        "匹伐他汀",
        "普芦卡必利",
        "曲美他嗪",
        "塞来昔布",
        "舍曲林",
        "坦索罗辛",
        "碳酸氢钠",
        "替格瑞洛",
        "托法替布",
        "维格列汀",
        "维生素B6",
        "西酞普兰",
        "西替利嗪",
        "缬沙坦",
        "盐酸达泊西汀片",
        "依托考昔",
        "乙胺丁醇",
        "右佐匹克隆",
        "左乙拉西坦",
        "阿莫西林"
      ],
      "min_value": null,
      "max_value": null
    },
    {
      "name": "bzcz",
      "type": "VARCHAR",
      "length": 255,
      "nullable": false,
      "primary_key": false,
      "semantic": "unknown",
      "enum_values": [],
      "value_pool": [
        "铝塑泡罩",
        "铝塑",
        "药用铝箔和聚氯乙烯/聚偏二氯乙烯固体药用复合硬片包装",
        "玻璃瓶",
        "PVC",
        "口服固体药用高密度聚乙烯瓶",
        "铝塑包装",
        "空",
        "其他",
        "聚氯乙烯固体药用硬片/药用铝箔",
        "复合膜袋包装",
        "双铝",
        "  ",
        "铝塑泡罩包装",
        "聚氯乙烯固体药用硬片，药用铝箔包装",
        "高密度聚乙烯",
        "聚酰胺/铝/聚氯乙烯冷冲压成型固体药用复合硬片和药用铝箔",
        "塑瓶",
        "聚氯乙烯固体药用硬片/药品包装用铝箔",
        "铝塑铝",
        "双铝包装",
        "安瓿",
        "复合膜"
      ],
      "min_value": null,
      "max_value": null
    },
    {
      "name": "mlgg",
      "type": "VARCHAR",
      "length": 255,
      "nullable": false,
      "primary_key": false,
      "semantic": "unknown",
      "enum_values": [],
      "value_pool": [
        "1mg",
        "2.5mg",
        "100mg",
        "0.75g",
        "30mg",
        "5mg",
        "10mg",
        "20mg",
        "0.3g",
        "0.2g",
        "0.5g",
        "40mg",
        "lmg",
        "25mg",
        "50mg",
        "0.5mg",
        "0.15g",
        "0.1g",
        "0.5g:4mg",
        "2mg",
        "0.2mg",
        "90mg",
        "80mg",
        "60mg",
        "120mg",
        "0.25g",
        "3mg",
        "10%(150ml:15g)",
        "5ml:500mg",
        "0.125g"
      ],
      "min_value": null,
      "max_value": null
    },
    {
      "name": "ypdm",
      "type": "VARCHAR",
      "length": 255,
      "nullable": true,
      "primary_key": false,
      "semantic": "unknown",
      "enum_values": [],
      "value_pool": [
        "XB01AFA281A001010101523",
        "XB01AFA281A001010201523",
        "XL01BCA300B001010102317",
        "XM01AXA165A001010201473",
        "XM01AXA165A001010301473",
        "XM01AXA165A001010701473",
        "XR05CBA198A001010109703",
        "XR05CBA198A001010209703",
        "XR05CBA198A001010309703",
        "XA02BCA211E005010204141",
        "XA02BCA211E005010304141",
        "XA02BCA211E005020404141",
        "XA02BCA211E005020504141",
        "XA02BCA211E005020104141",
        "XA02BCA211E005020304141",
        "XR06AXD078A001010505801",
        "XA03FAD173A001010302461",
        "XA10BAE021A010010202770",
        "XA10BAE021A001010102770",
        "XA10BAE021A001010202770",
        "XM04AAF670A001010101729",
        "XM04AAF670A001010401729",
        "XG04CBF019A001020103098",
        "XG04CBF019A001020203098",
        "XN06ABF098E001010202920",
        "XB03BAJ038A001010105337",
        "XB03BAJ038A001010205337",
        "XL01BCK023A001010104021",
        "XL01BCK023A001020104021",
        "XN05AHK094A001030104917",
        "XN05AHK094A001010104917",
        "XN05AHK094A001020104917",
        "XL02BGL020A001010104641",
        "XN05AHL195A001010101436",
        "XR03DCM082N001010301521",
        "XC01EBQ102A001010101645",
        "XC01EBQ102A001010201645",
        "XC01EBQ102A001010301645",
        "XN06ABS066A001010104647",
        "XN06ABS066A001010304647",
        "XG04CAT011E003010204489",
        "XA02AHT018A001010104827",
        "XB01ACT157A001010110104",
        "XA11HAW041A001010102000",
        "XN06ABX016A001010102292",
        "XN06ABX016A001010202292",
        "XN06ABX016E001010202292",
        "XN06ABX016A001010302292",
        "XR06AEX017A001010204012",
        "XC09CAX143E001010100560",
        "XC09CAX143E001010200560",
        "XC09CAX143E001010300560",
        "XM01AHY094A001010102181",
        "XM01AHY094A001010202181",
        "XM01AHY094A001020102181",
        "XJ04AKY105A001010100290",
        "XN05CFY202A001010102041",
        "XN03AXZ075X001010109568",
        "XJ01CAA040N001010105006",
        "XJ01CAA040N001010205006",
        "XJ01MAM134B002010105759",
        "XS01AEZ074G010010101749",
        "XJ01DDT068E001010101444",
        "XJ01DDT068E001010201444",
        "XJ01DCT072E001010100407",
        "XJ01FAK067A001010106988",
        "XJ01FAK067A001020106988"
      ],
      "min_value": null,
      "max_value": null
    },
    {
      "name": "cpi",
      "type": "INT",
      "length": null,
      "nullable": false,
      "primary_key": false,
      "semantic": "unknown",
      "enum_values": [],
      "value_pool": [
        "187558",
        "104577",
        "187411",
        "107837",
        "109390",
        "27529",
        "27528",
        "187407",
        "186560",
        "98225",
        "100769",
        "185451",
        "105611",
        "186556",
        "99597",
        "96881",
        "98899",
        "186558",
        "187410",
        "187432",
        "109793",
        "103394",
        "106588",
        "187424",
        "96662",
        "94706",
        "187427",
        "56233",
        "36248",
        "187553",
        "106079",
        "29935",
        "29936",
        "187581",
        "101228",
        "185411",
        "186176",
        "110122",
        "110138",
        "102805",
        "103736",
        "45761",
        "83145",
        "84833",
        "109389",
        "184995",
        "34718",
        "96257",
        "34578",
        "49417",
        "96603",
        "186302",
        "92080",
        "101087",
        "187438",
        "187413",
        "187414",
        "100337",
        "105625",
        "110235",
        "186851",
        "187452",
        "184765",
        "105690",
        "184782",
        "109453",
        "109454",
        "105121",
        "186292",
        "74193",
        "90936",
        "43873",
        "187404",
        "28407",
        "68526",
        "99853",
        "109659",
        "187420",
        "106661",
        "96400",
        "98711",
        "108146",
        "187217",
        "30574",
        "105283",
        "103239",
        "100408",
        "99030",
        "109551",
        "103197",
        "187426",
        "107238",
        "187429",
        "106635",
        "95666",
        "65442",
        "94167",
        "87112",
        "186323",
        "105621"
      ],
      "min_value": 27528.0,
      "max_value": 187581.0
    },
    {
      "name": "pzmc",
      "type": "VARCHAR",
      "length": 255,
      "nullable": false,
      "primary_key": false,
      "semantic": "company_name",
      "enum_values": [],
      "value_pool": [
        "阿那曲唑口服常释剂型",
        "阿哌沙班口服常释剂型",
        "阿扎胞苷注射剂",
        "氨基葡萄糖口服常释剂型",
        "氨溴索口服常释剂型",
        "奥氮平口腔崩解片",
        "奥美拉唑口服常释剂型",
        "布洛芬缓释控释剂型",
        "布洛芬颗粒剂",
        "地氯雷他定口服常释剂型",
        "多潘立酮口服常释剂型",
        "二甲双胍缓释控释剂型",
        "二甲双胍口服常释剂型",
        "非布司他口服常释剂型",
        "非那雄胺口服常释剂型",
        "氟西汀口服常释剂型",
        "枸橼酸西地那非片",
        "甲钴胺口服常释剂型",
        "卡培他滨口服常释剂型",
        "卡托普利口服常释剂型",
        "喹硫平口服常释剂型",
        "来曲唑口服常释剂型",
        "氯氮平口服常释剂型",
        "美金刚口服常释剂型",
        "孟鲁司特咀嚼片",
        "孟鲁司特颗粒剂",
        "匹伐他汀口服常释剂型",
        "普芦卡必利口服常释剂型",
        "曲美他嗪口服常释剂型",
        "塞来昔布口服常释剂型",
        "舍曲林口服常释剂型",
        "坦洛新（坦索罗辛）缓释控释剂型",
        "碳酸氢钠口服常释剂型",
        "替格瑞洛口服常释剂型",
        "托法替布口服常释剂型",
        "维格列汀口服常释剂型",
        "维生素B6口服常释剂型",
        "西酞普兰口服常释剂型",
        "西替利嗪口服常释剂型",
        "缬沙坦口服常释剂型",
        "盐酸达泊西汀片",
        "依托考昔口服常释剂型",
        "乙胺丁醇口服常释剂型",
        "右佐匹克隆口服常释剂型",
        "左乙拉西坦口服液体剂",
        "左乙拉西坦注射用浓溶液",
        "阿莫西林颗粒剂"
      ],
      "min_value": null,
      "max_value": null
    }
  ]
}