{
  "file_name": "汶上县高新技术企业认定信息202506271837.xlsx",
  "table_name": "汶上县高新技术企业认定信息202506271837",
  "row_count": 141,
  "columns": [
    "qymc",
    "rdnf",
    "gxjsly",
    "sszj",
    "zsbh"
  ],
  "fields": [
    {
      "name": "qymc",
      "type": "VARCHAR",
      "length": 255,
      "nullable": false,
      "primary_key": false,
      "semantic": "company_name",
      "enum_values": [],
      "value_pool": [
        "山东世腾运动设备有限公司",
        "山东兰通机电有限公司",
        "山东环亚液压机械有限公司",
        "山东裕能电力器材有限公司",
        "济宁高洁新型建材有限公司",
        "山东鑫海能润滑油股份有限公司",
        "山东大佳机械有限公司",
        "山东尚儒弘毅精细化工有限公司",
        "汶上县众鑫机械有限公司",
        "山东聚合管业有限公司",
        "济宁协力能源有限公司",
        "山东济宁丰泽农业科技有限公司",
        "济宁为民制药有限公司",
        "山东升泓电力科技有限公司",
        "山东中都机器有限公司",
        "山东驰胜智能科技有限公司",
        "山东飞宏工程机械有限公司",
        "济宁万彩高分子材料有限公司",
        "金成技术股份有限公司",
        "山东精良海纬机械有限公司",
        "山东新汇源喷雾科技有限公司",
        "山东力加力钢结构有限公司",
        "山东华首重工有限公司",
        "山东正权纺织材料股份有限公司",
        "济宁星亚化工有限公司",
        "济宁长胜新材料股份有限公司",
        "济宁中银电化有限公司",
        "济宁圣地农林机械有限公司",
        "济宁北汇玻璃有限公司",
        "山东兴诺工贸股份有限公司",
        "山东安迪新型材料有限公司",
        "山东沃尔鑫机械有限公司",
        "山东省汶上县丝杠有限责任公司",
        "汶上县鲁豪木业有限公司",
        "济宁王诺模具有限公司",
        "山东欧利德智能重工机械有限公司",
        "汶上海纬机车配件有限公司",
        "山东华准机械有限公司",
        "山东钰泰化工有限公司",
        "山东华尚电气有限公司",
        "山东亚特美环境科技有限公司",
        "济宁市邦达煤化工有限公司",
        "山东北骏重工有限公司",
        "山东特亚供水设备有限公司",
        "济宁译择新材料科技有限公司",
        "山东佳创机械有限公司",
        "汶上县永丰机械有限公司",
        "中东金润新材料有限公司",
        "山东华首新能源技术有限公司",
        "山东华力机电有限公司",
        "济宁广进新型材料有限公司",
        "济宁安鑫养殖有限公司",
        "山东轩安新型建材有限公司",
        "汶上县金振机械制造有限公司",
        "汶上县恒安钢结构有限公司",
        "山东奥特美森智能装备有限公司",
        "汶上如意润发纺织有限公司",
        "济宁聚全建材科技有限公司",
        "济宁建强机械有限公司",
        "山东佳润精密机械制造有限公司",
        "山东鲁正水处理设备有限公司",
        "山东领秀新能源科技有限公司",
        "山东京首孝慈医用设备有限公司",
        "山东瑞乐装备制造有限公司",
        "济宁瑞华电子技术有限公司",
        "新风光电子科技股份有限公司",
        "山东鹰联光电科技股份有限公司",
        "凯尔菱电（山东）电梯有限公司",
        "济宁金筑新型建材科技有限公司",
        "汶上县华诚机械有限公司",
        "济宁联威车轮制造有限公司",
        "山东土木启生物科技有限公司",
        "济宁鸿启建设工程检测有限公司",
        "山东大拇指喷雾设备有限公司",
        "山东迪格重工机械有限公司",
        "济宁洪博胜易新材料有限公司",
        "山东西曼克技术有限公司",
        "济宁冠豪木业有限公司",
        "山东天润源生物科技有限公司",
        "山东拓瑞多新材料有限公司",
        "汶上县瑞尔特机床设备有限公司",
        "山东新花源纺织有限公司",
        "山东亿昌装配式建筑科技有限公司",
        "山东大汶河融媒体（集团）有限公司",
        "山东瑞晴化工有限公司",
        "济宁德耐弛新能源有限公司",
        "山东永耐特索具有限公司",
        "山东华首传动科技有限公司",
        "济宁金藤薯业科技有限公司",
        "山东辰欣佛都药业股份有限公司",
        "山东金秋农牧科技股份有限公司",
        "山东康姆勒发电机有限公司",
        "汶上齐力机械加工有限公司",
        "山东瑞程数据科技有限公司",
        "济宁市恒众无纺材料科技有限公司",
        "山东鲁玻玻璃科技有限公司",
        "山东质能新型材料有限公司",
        "山东洲蓝环保科技有限公司",
        "济宁旭鑫工贸有限公司",
        "山东锦都食品有限公司"
      ],
      "min_value": null,
      "max_value": null
    },
    {
      "name": "rdnf",
      "type": "VARCHAR",
      "length": 255,
      "nullable": false,
      "primary_key": false,
      "semantic": "unknown",
      "enum_values": [
        "2021",
        "2022",
        "2023"
      ],
      "value_pool": [
        "2021",
        "2022",
        "2023"
      ],
      "min_value": null,
      "max_value": null
    },
    {
      "name": "gxjsly",
      "type": "VARCHAR",
      "length": 255,
      "nullable": false,
      "primary_key": false,
      "semantic": "unknown",
      "enum_values": [
        "先进制造与自动化",
        "新材料",
        "新能源与节能",
        "生物与新医药",
        "资源与环境",
        "高技术服务",
        "电子信息"
      ],
      "value_pool": [
        "先进制造与自动化",
        "新材料",
        "新能源与节能",
        "生物与新医药",
        "资源与环境",
        "高技术服务",
        "电子信息"
      ],
      "min_value": null,
      "max_value": null
    },
    {
      "name": "sszj",
      "type": "VARCHAR",
      "length": 255,
      "nullable": false,
      "primary_key": false,
      "semantic": "unknown",
      "enum_values": [],
      "value_pool": [
        "义桥镇",
        "杨店镇",
        "中都街道",
        "郭楼镇",
        "南站街道",
        "康驿镇",
        "军屯乡",
        "郭仓镇",
        "经济开发区",
        "汶上街道",
        "寅寺镇",
        "南旺镇",
        "次邱镇",
        "刘楼镇",
        "苑庄镇",
        "白石镇",
        "开发区"
      ],
      "min_value": null,
      "max_value": null
    },
    {
      "name": "zsbh",
      "type": "INT",
      "length": null,
      "nullable": false,
      "primary_key": true,
      "semantic": "id",
      "enum_values": [],
      "value_pool": [
        "GR202137000061",
        "GR202137000249",
        "GR202137000613",
        "GR202137000903",
        "GR202137001137",
        "GR202137001282",
        "GR202137001322",
        "GR202137001401",
        "GR202137001568",
        "GR202137001588",
        "GR202137001698",
        "GR202137001962",
        "GR202137002369",
        "GR202137002503",
        "GR202137003046",
        "GR202137003066",
        "GR202137003416",
        "GR202137003692",
        "GR202137004107",
        "GR202137004317",
        "GR202137004490",
        "GR202137004873",
        "GR202137004903",
        "GR202137005559",
        "GR202137005915",
        "GR202137005991",
        "GR202137006280",
        "GR202137006540",
        "GR202137007030",
        "GR202237006151",
        "GR202237003701",
        "GR202237006340",
        "GR202237004002",
        "GR202237006127",
        "GR202237007680",
        "GR202237003146",
        "GR202237002987",
        "GR202237007587",
        "GR202237003892",
        "GR202237005080",
        "GR202237004336",
        "GR202237007294",
        "GR202237005016",
        "GR202237007892",
        "GR202237006648",
        "GR202237003015",
        "GR202237004813",
        "GR202237006453",
        "GR202237006498",
        "GR202237006603",
        "GR202237007414",
        "GR202237006928",
        "GR202237006768",
        "GR202237008034",
        "GR202237005235",
        "GR202237006044",
        "GR202237002984",
        "GR202237006124",
        "GR202237000454",
        "GR202237001648",
        "GR202237001345",
        "GR202237001877",
        "GR202237000109",
        "GR202237001775",
        "GR202237001481",
        "GR202337002991",
        "GR202337001719",
        "GR202337002802",
        "GR202337001148",
        "GR202337003079",
        "GR202337001906",
        "GR202337002836",
        "GR202337000359",
        "GR202337000415",
        "GR202337002283",
        "GR202337003623",
        "GR202337003543",
        "GR202337002660",
        "GR202337001438",
        "GR202337001520",
        "GR202337002408",
        "GR202337002810",
        "GR202337002492",
        "GR202337001547",
        "GR202337001720",
        "GR202337003476",
        "GR202337002913",
        "GR202337003040",
        "GR202337002455",
        "GR202337004527",
        "GR202337005391",
        "GR202337005104",
        "GR202337005100",
        "GR202337003940",
        "GR202337006705",
        "GR202337004296",
        "GR202337009825",
        "GR202337008281",
        "GR202337008828",
        "GR202337009461"
      ],
      "min_value": null,
      "max_value": null
    }
  ]
}