{
  "file_name": "鱼台县农业农村局_鱼台县农业农村局帮扶责任人帮扶台账信息202506271757.xlsx",
  "table_name": "鱼台县农业农村局_鱼台县农业农村局帮扶责任人帮扶台账信息202506271757",
  "row_count": 94,
  "columns": [
    "bfrdw",
    "szz",
    "bfpkh",
    "szc",
    "bfr"
  ],
  "fields": [
    {
      "name": "bfrdw",
      "type": "VARCHAR",
      "length": 255,
      "nullable": false,
      "primary_key": false,
      "semantic": "company_name",
      "enum_values": [
        "鱼台县农业农村局",
        "农业农村局"
      ],
      "value_pool": [
        "鱼台县农业农村局",
        "农业农村局"
      ],
      "min_value": null,
      "max_value": null
    },
    {
      "name": "szz",
      "type": "VARCHAR",
      "length": 255,
      "nullable": false,
      "primary_key": false,
      "semantic": "unknown",
      "enum_values": [
        "张黄镇",
        "王鲁镇",
        "王庙镇",
        "李阁镇",
        "张黄镇人民政府"
      ],
      "value_pool": [
        "张黄镇",
        "王鲁镇",
        "王庙镇",
        "李阁镇",
        "张黄镇人民政府"
      ],
      "min_value": null,
      "max_value": null
    },
    {
      "name": "bfpkh",
      "type": "VARCHAR",
      "length": 255,
      "nullable": false,
      "primary_key": false,
      "semantic": "unknown",
      "enum_values": [],
      "value_pool": [
        "赵长海",
        "马培旺",
        "常光明",
        "卜庆江",
        "常秀记",
        "赵绍平",
        "常秀军",
        "赵宝民",
        "李继国",
        "王延国",
        "常春",
        "赵绍中",
        "许成芝",
        "李涛",
        "李现军",
        "曹桂荣",
        "秦景芝",
        "巩绘锦",
        "张桂英",
        "李玉玲",
        "陈安文",
        "许四运",
        "杨秀兰",
        "卞学礼",
        "张乃俊",
        "李清坡",
        "李景明",
        "许天灵",
        "卞领章",
        "张乃科",
        "李景帅",
        "李宁波",
        "朱汉青",
        "李龙防",
        "高树松",
        "梁勋超",
        "姚翠兰",
        "王先玲",
        "王黄氏",
        "王继民",
        "樊维同",
        "樊纯福",
        "樊佑宣",
        "樊维存",
        "樊佑祥",
        "樊维强",
        "樊纯刚",
        "樊维书",
        "樊栋峰",
        "马汉怀",
        "樊佑刚",
        "鹿占玲",
        "樊超武",
        "李传秀",
        "王停停",
        "古存财",
        "李延磊",
        "常世仲",
        "李正华",
        "于秀侠",
        "常世昌",
        "吴清银",
        "羿庆林",
        "赵绍来",
        "韩小三",
        "韩兆领",
        "吴渭洪",
        "吴东生",
        "董庆香",
        "吴渭新",
        "柴有朋",
        "郝运先",
        "柴秀军",
        "郝敬华",
        "杨井民",
        "刘运芝",
        "杨桂兰",
        "吴传立",
        "吴传东",
        "宋洪思",
        "张连民",
        "张如义",
        "张景忠",
        "徐玉喜",
        "张福成",
        "张克召",
        "张克宣",
        "张永振",
        "张景瑞",
        "强留仁",
        "强全仁",
        "梁*超",
        "姚*兰",
        "王*玲"
      ],
      "min_value": null,
      "max_value": null
    },
    {
      "name": "szc",
      "type": "VARCHAR",
      "length": 255,
      "nullable": false,
      "primary_key": false,
      "semantic": "unknown",
      "enum_values": [
        "常柳行村",
        "卞李村",
        "杈王村",
        "樊庄村",
        "田庙村",
        "古李村",
        "吴家村",
        "张庄村",
        "强家村"
      ],
      "value_pool": [
        "常柳行村",
        "卞李村",
        "杈王村",
        "樊庄村",
        "田庙村",
        "古李村",
        "吴家村",
        "张庄村",
        "强家村"
      ],
      "min_value": null,
      "max_value": null
    },
    {
      "name": "bfr",
      "type": "VARCHAR",
      "length": 255,
      "nullable": false,
      "primary_key": false,
      "semantic": "unknown",
      "enum_values": [],
      "value_pool": [
        "赵千里",
        "金西勇",
        "高树林",
        "杨卫华",
        "葛军",
        "解剑南",
        "刘安敏",
        "刘茂品",
        "刘志磊",
        "田虎",
        "闫运立",
        "刘建厂",
        "薛垂喜",
        "李月山",
        "刘化明",
        "沙海斌",
        "王亮",
        "刘希柱",
        "刘永",
        "陈培峰",
        "聂孟阳",
        "薛保华",
        "赵兴华",
        "闫茂营",
        "孙厚强",
        "卜凡伍",
        "赵仰启",
        "刘*厂",
        "薛*喜"
      ],
      "min_value": null,
      "max_value": null
    }
  ]
}