{
  "file_name": "鱼台县财政局_商城采购目录信息202506241252.xlsx",
  "table_name": "鱼台县财政局_商城采购目录信息202506241252",
  "row_count": 112,
  "columns": [
    "dypmbm",
    "cgfssm",
    "dypmmc",
    "cgmllb",
    "mc"
  ],
  "fields": [
    {
      "name": "dypmbm",
      "type": "VARCHAR",
      "length": 255,
      "nullable": false,
      "primary_key": false,
      "semantic": "unknown",
      "enum_values": [],
      "value_pool": [
        "G0102010107",
        "G0102010199",
        "G01020106010\n\n3",
        "G0102081001",
        "G0102021001",
        "G0102021003",
        "G01020206",
        "G01020106099\n\n9",
        "G01020301",
        "G0102010201",
        "G01020102020\n\n1",
        "G01020618020\n\n5",
        "G01020618020\n\n8",
        "G01020618020\n\n7",
        "G0102091001",
        "G0102091102",
        "G0102091201",
        "G0102091203",
        "G0102091106",
        "G0102091205",
        "G0102091301",
        "G0102061805",
        "G0102061808",
        "G0102061807",
        "G01020618010\n\n1",
        "G01020618030\n\n1",
        "G01020618039\n\n9",
        "G01020618030\n\n2",
        "G01020618020\n\n1",
        "G01020618030\n\n3",
        "G01060802",
        "G01090201",
        "G01090202",
        "G01090203/G0",
        "G01090205",
        "G01020106070\n\n1",
        "G01020106070\n\n2",
        "G0102091299",
        "G01020209",
        "G01020109",
        "G01070305",
        "G0102010508",
        "G0102010701",
        "G01090402",
        "G01090301",
        "G01090302",
        "G01090199",
        "G01090103",
        "G01090102",
        "G01090401",
        "G0102021401",
        "G01090403",
        "G01080204",
        "G01080206",
        "G01080205",
        "G01032801",
        "G0102061727",
        "G01020807010\n\n1",
        "G0102100901",
        "G0102061908",
        "G0102061915",
        "G01020615100\n\n1",
        "G019999",
        "G0107030301",
        "G0107030302",
        "G01060812",
        "G0107030201",
        "G0107030202",
        "G0107030203",
        "G0107030204",
        "G0107030205",
        "G0107030206",
        "G0107030208",
        "G0107030209",
        "G01032027",
        "G01090501",
        "G01090599",
        "G01090503",
        "G01090502",
        "G01033603",
        "G01033622"
      ],
      "min_value": null,
      "max_value": null
    },
    {
      "name": "cgfssm",
      "type": "VARCHAR",
      "length": 255,
      "nullable": false,
      "primary_key": false,
      "semantic": "text",
      "enum_values": [
        "直购或竞价",
        "竞价"
      ],
      "value_pool": [
        "直购或竞价",
        "竞价"
      ],
      "min_value": null,
      "max_value": null
    },
    {
      "name": "dypmmc",
      "type": "VARCHAR",
      "length": 255,
      "nullable": false,
      "primary_key": false,
      "semantic": "company_name",
      "enum_values": [],
      "value_pool": [
        "其他货物",
        "传真通信设\n备",
        "速印机",
        "装订机",
        "电⼦⽩板",
        "其他图形图\n像输⼊设备",
        "货⻋",
        "路由器",
        "以太⽹交换\n机",
        "空⽓净化设\n备",
        "调湿调温机",
        "取暖器",
        "普通电视设\n备  （电视机）",
        "通⽤摄像机",
        "录放⾳机",
        "⾳频功率放\n⼤器设备  （功\n放设备）",
        "激光视盘机",
        "⾳响电视组\n合机",
        "⾳视频播放\n设备",
        "烹调电器",
        "热⽔器",
        "饮⽔器",
        "电冰箱",
        "洗⾐机",
        "其他清洁卫\n⽣电器",
        "吸尘器",
        "⻛扇",
        "洗碗机",
        "炊事机械",
        "⿎粉盒",
        "粉盒",
        "喷墨盒/墨⽔",
        "⾊带",
        "键盘",
        "⿏标器",
        "其他⾳频设\n备",
        "刻录机",
        "计算机设备\n零部件",
        "箱、包和类似\n制品",
        "移动存储设\n备",
        "机柜",
        "笔",
        "墨⽔",
        "颜料",
        "其他纸制品",
        "信封",
        "信纸",
        "⽂具",
        "计算器",
        "教具",
        "单证",
        "本册",
        "票据",
        "钞票处理设\n备",
        "电源插座和\n转换器",
        "普通电话机",
        "钟",
        "室内照明灯\n具",
        "⼿电筒",
        "原电池和原\n电池组",
        "其他不另分\n类的物品",
        "台布  （桌布）",
        "⽑⼱",
        "杯⼦  （含纸\n杯 、碟⼦ 、盘\n⼦ 、筷⼦ 、勺\n⼦ 、碗 、保温\n瓶",
        "床褥单",
        "被⾯",
        "枕套",
        "被罩",
        "床罩",
        "毯⼦",
        "⽑⼱被",
        "枕⼱",
        "防疫、防护卫\n⽣装备及器\n具",
        "卫⽣⽤纸制\n品",
        "其他清洁⽤\n具",
        "肥  （⾹）  皂和\n合成洗涤剂",
        "消毒杀菌⽤\n品",
        "球类设备",
        "棋牌类运动\n设备"
      ],
      "min_value": null,
      "max_value": null
    },
    {
      "name": "cgmllb",
      "type": "VARCHAR",
      "length": 255,
      "nullable": false,
      "primary_key": false,
      "semantic": "status",
      "enum_values": [
        "分散采购⽬录"
      ],
      "value_pool": [
        "分散采购⽬录"
      ],
      "min_value": null,
      "max_value": null
    },
    {
      "name": "mc",
      "type": "VARCHAR",
      "length": 255,
      "nullable": false,
      "primary_key": false,
      "semantic": "company_name",
      "enum_values": [],
      "value_pool": [
        "平板式电脑",
        "台式图形⼯作站",
        "移动图形  ⼯\n作站",
        "热式打印机",
        "传真机",
        "速印机",
        "装订机",
        "电⼦⽩板",
        "速拍仪",
        "⽪卡⻋",
        "路由器",
        "交换机",
        "空⽓净化器",
        "加湿器",
        "除湿机",
        "电暖器",
        "电视机",
        "摄像机",
        "录⾳笔",
        "功放机",
        "蓝光/DVD 播\n放机",
        "⾳响",
        "家庭影院",
        "微波炉",
        "电饭煲",
        "热⽔器(太阳\n能 、  电 、  空⽓\n能)",
        "电⽔壶",
        "饮⽔机",
        "净⽔器",
        "电冰箱",
        "洗⾐机",
        "消毒柜",
        "吸尘器",
        "电⻛扇",
        "洗碗机",
        "吸油烟机",
        "燃⽓灶",
        "硒⿎  （粉盒）",
        "碳粉",
        "墨盒",
        "⾊带",
        "键盘",
        "⿏标",
        "⽿⻨",
        "光盘刻录机",
        "⿏标垫",
        "电脑包",
        "移动硬盘",
        "闪存盘 （U 盘）",
        "光盘",
        "机柜",
        "机械硬盘",
        "固态硬盘",
        "计算机内存",
        "书写⼯具钢\n笔 、铅笔 、  圆\n珠笔、签字笔、\n⽑笔、勾线笔、\n⻢克笔  （记号\n笔）、⽔彩笔、\n粉笔）",
        "墨⽔",
        "颜料",
        "本册/便签  （笔\n记本 、便签、\n标签 、奖状、\n证书、⼝取纸、\n其他纸张  （除\n复印纸）",
        "信封",
        "信纸",
        "办公⽂具  （胶\n带 、胶⽔ 、订\n书机、起订器、\n切纸⼑ 、⼤头\n针 、  回形针、\n剪 ⼑ 、  笔筒、\n票夹、橡⽪筋、\n尺⼦ 、橡⽪ 、\n光盘、订书钉、\n绳⼦）",
        "计算器",
        "地球仪",
        "⽂件收纳  （⽂\n件夹、⽂件袋、\n⽂件筐 、档案\n盒 、  资料册、\n书报架 、名⽚\n盒 、档案袋、\n证件套）",
        "凭证",
        "账本",
        "单据",
        "复写纸",
        "印台  （印油）",
        "点  （验）  钞机",
        "插排",
        "电话机",
        "钟表",
        "台灯",
        "⼿电筒",
        "电池",
        "⾬具",
        "桌布",
        "⽑⼱",
        "餐具",
        "床褥单",
        "被⾯",
        "枕套",
        "被罩",
        "床罩",
        "毯⼦",
        "⽑⼱被",
        "枕⼱",
        "防护装备  （⼝\n罩 、  防护服、\n隔离⾐）",
        "卫⽣纸品  （抽\n纸 、卷纸 、湿\n⼱）",
        "清洁⼯具  （拖\n把、扫把簸萁、\n垃圾袋 、垃圾\n桶 、⽔桶 、脸\n盆 、⼿套 、抹\n布）",
        "洗洁精 、  洗⾐\n液 、  洗⾐粉、\n肥皂、清洁剂、\n洗⼿液",
        "消毒液",
        "乒乓球",
        "⽻⽑球",
        "⾜球",
        "篮球",
        "排球",
        "⽹球",
        "棋牌"
      ],
      "min_value": null,
      "max_value": null
    }
  ]
}