{
  "file_name": "鱼台县人社局_企业离退休人员冬季取暖费发放明细表202508010333.xlsx",
  "table_name": "鱼台县人社局_企业离退休人员冬季取暖费发放明细表202508010333",
  "row_count": 12351,
  "columns": [
    "dwbh",
    "ffny",
    "btje",
    "shbzhm",
    "bfqk",
    "姓名",
    "ltxrq",
    "btmc"
  ],
  "fields": [
    {
      "name": "dwbh",
      "type": "INT",
      "length": null,
      "nullable": false,
      "primary_key": true,
      "semantic": "id",
      "enum_values": [
        "824000005.0",
        "824100001.0",
        "824100002.0",
        "824140011.0",
        "824171202.0",
        "824172001.0",
        "824211001.0",
        "824222002.0",
        "824482001.0"
      ],
      "value_pool": [
        "824000005.0",
        "824100001.0",
        "824100002.0",
        "824140011.0",
        "824171202.0",
        "824172001.0",
        "824211001.0",
        "824222002.0",
        "824482001.0"
      ],
      "min_value": 82469100.0,
      "max_value": 3708977277.0
    },
    {
      "name": "ffny",
      "type": "DATETIME",
      "length": null,
      "nullable": false,
      "primary_key": false,
      "semantic": "unknown",
      "enum_values": [
        "2020-12-01 00:00:00"
      ],
      "value_pool": [
        "2020-12-01 00:00:00"
      ],
      "min_value": null,
      "max_value": null
    },
    {
      "name": "btje",
      "type": "INT",
      "length": null,
      "nullable": false,
      "primary_key": false,
      "semantic": "unknown",
      "enum_values": [
        "1700"
      ],
      "value_pool": [
        "1700"
      ],
      "min_value": -1700.0,
      "max_value": 1700.0
    },
    {
      "name": "shbzhm",
      "type": "VARCHAR",
      "length": 255,
      "nullable": false,
      "primary_key": false,
      "semantic": "unknown",
      "enum_values": [],
      "value_pool": [
        "370827********1621",
        "370827********0030",
        "370827********0021",
        "370827********0027",
        "370827********0012",
        "370827********0811",
        "370827********0026",
        "370827********0018",
        "370827********0046",
        "370827********0022",
        "370827********002X",
        "370827********0063",
        "370827********0028",
        "370827********0062",
        "370827********0034",
        "370827********001X",
        "370827********0014",
        "370827********0023",
        "370827********0020",
        "370827********0015",
        "370827********0037",
        "370827********0049",
        "370827********004X",
        "370827********0084",
        "370827********0040",
        "370827********0045",
        "350127********0558",
        "370827********201X",
        "370827********233X",
        "370827********0305",
        "370827********1348",
        "410927********7102",
        "372522********7267",
        "370827********1646",
        "370827********0105",
        "370827********1628",
        "370827********1316",
        "370827********3522",
        "370827********1315",
        "370827********1324",
        "370827********1626",
        "370827********3024",
        "370827********1610",
        "410102********4542",
        "370827********0828",
        "370826********5144",
        "370827********1311",
        "370827********3740",
        "370827********1069",
        "370827********1039",
        "370827********131X",
        "370827********0513",
        "370827********3767",
        "370827********1369",
        "370826********5160",
        "370827********1325",
        "370828********1338",
        "370827********3543",
        "370827********1339",
        "370827********2822",
        "370827********1623",
        "370827********1629",
        "370827********3784",
        "370827********1046",
        "370827********1015",
        "370827********1086",
        "370827********0081",
        "370827********2541",
        "370827********2540",
        "412301********1524",
        "370827********2538",
        "370827********2543",
        "370828********0311",
        "370827********0017",
        "370827********1624",
        "370827********0082",
        "370827********3224",
        "370827********0121",
        "370827********0048",
        "370827********3067",
        "370827********0044",
        "370827********2049"
      ],
      "min_value": null,
      "max_value": null
    },
    {
      "name": "bfqk",
      "type": "VARCHAR",
      "length": 255,
      "nullable": false,
      "primary_key": false,
      "semantic": "unknown",
      "enum_values": [
        "已拨付"
      ],
      "value_pool": [
        "已拨付"
      ],
      "min_value": null,
      "max_value": null
    },
    {
      "name": "姓名",
      "type": "VARCHAR",
      "length": 255,
      "nullable": false,
      "primary_key": false,
      "semantic": "person_name",
      "enum_values": [],
      "value_pool": [
        "王**",
        "杨**",
        "逯**",
        "段**",
        "李**",
        "曹**",
        "韩**",
        "随**",
        "马**",
        "魏**",
        "殷**",
        "安**",
        "宋**",
        "刘**",
        "祁**",
        "秦**",
        "田**",
        "代**",
        "张**",
        "袁**",
        "姚**",
        "沈**",
        "郑**",
        "郭**",
        "陈**",
        "周**",
        "鲁**",
        "岳**",
        "赵**",
        "薛**",
        "丁**",
        "董**",
        "樊**",
        "吕**",
        "蒿**",
        "甄**",
        "程**",
        "朱**",
        "闫**",
        "骆**",
        "罗**",
        "孟**",
        "任**",
        "翟**"
      ],
      "min_value": null,
      "max_value": null
    },
    {
      "name": "ltxrq",
      "type": "DATETIME",
      "length": null,
      "nullable": false,
      "primary_key": false,
      "semantic": "time",
      "enum_values": [],
      "value_pool": [
        "2014-12-01 00:00:00",
        "1993-10-01 00:00:00",
        "1997-09-01 00:00:00",
        "2000-07-01 00:00:00",
        "1997-11-01 00:00:00",
        "2004-11-01 00:00:00",
        "2000-09-01 00:00:00",
        "1994-02-01 00:00:00",
        "1997-02-01 00:00:00",
        "1999-08-01 00:00:00",
        "1996-10-01 00:00:00",
        "1996-09-01 00:00:00",
        "1999-12-01 00:00:00",
        "2000-01-01 00:00:00",
        "1999-01-01 00:00:00",
        "2000-12-01 00:00:00",
        "1983-03-01 00:00:00",
        "2002-12-01 00:00:00",
        "2005-10-01 00:00:00",
        "2007-10-01 00:00:00",
        "1997-04-01 00:00:00",
        "2003-09-01 00:00:00",
        "1986-12-01 00:00:00",
        "2007-04-01 00:00:00",
        "2001-12-01 00:00:00",
        "1999-07-01 00:00:00",
        "2010-04-01 00:00:00",
        "2004-12-01 00:00:00",
        "2006-11-01 00:00:00",
        "1998-11-01 00:00:00",
        "2011-01-01 00:00:00",
        "2019-03-01 00:00:00",
        "2019-04-01 00:00:00",
        "2017-06-01 00:00:00",
        "2019-05-31 00:00:00",
        "2013-02-01 00:00:00",
        "2014-02-01 00:00:00",
        "2014-03-01 00:00:00",
        "2013-10-01 00:00:00",
        "2018-02-01 00:00:00",
        "2015-01-01 00:00:00",
        "2015-10-01 00:00:00",
        "2013-03-01 00:00:00",
        "2013-07-01 00:00:00",
        "2013-06-01 00:00:00",
        "2014-06-01 00:00:00",
        "2013-11-01 00:00:00",
        "2013-01-01 00:00:00",
        "2016-11-01 00:00:00",
        "2013-04-01 00:00:00",
        "2015-12-01 00:00:00",
        "2015-06-01 00:00:00",
        "2013-05-01 00:00:00",
        "2014-01-01 00:00:00",
        "2013-09-01 00:00:00",
        "2013-08-01 00:00:00",
        "2015-03-01 00:00:00",
        "2020-01-01 00:00:00",
        "2010-12-16 00:00:00",
        "2018-06-01 00:00:00",
        "2012-05-01 00:00:00",
        "2020-09-01 00:00:00",
        "2015-05-01 00:00:00",
        "2014-10-01 00:00:00",
        "2013-12-01 00:00:00",
        "2011-02-01 00:00:00",
        "2010-12-01 00:00:00"
      ],
      "min_value": null,
      "max_value": null
    },
    {
      "name": "btmc",
      "type": "VARCHAR",
      "length": 255,
      "nullable": false,
      "primary_key": false,
      "semantic": "company_name",
      "enum_values": [
        "冬季取暖费"
      ],
      "value_pool": [
        "冬季取暖费"
      ],
      "min_value": null,
      "max_value": null
    }
  ]
}